zenetics/__init__.py
zenetics/api/__init__.py
zenetics/api/zenetics_api_client.py
zenetics/cli/__init__.py
zenetics/cli/check.py
zenetics/cli/common.py
zenetics/cli/docs.py
zenetics/cli/help.py
zenetics/cli/main.py
zenetics/cli/run.py
zenetics/cli/testsuites.py
zenetics/models/__init__.py
zenetics/models/base.py
zenetics/models/evaluation_batch.py
zenetics/models/evaluator.py
zenetics/models/generation.py
zenetics/models/test_case.py
zenetics/models/test_run.py
zenetics/models/test_suite.py
zenetics/setup_checker.py
zenetics/testrunners/test_runner_base.py
zenetics/testrunners/test_runner_server.py
zenetics/utils/__init__.py
zenetics/utils/convert_result.py
zenetics/utils/environment.py
zenetics/utils/test_run_formatter.py
zenetics/utils/validate_json.py
zenetics-0.3.3.dist-info/METADATA
zenetics-0.3.3.dist-info/WHEEL
zenetics-0.3.3.dist-info/entry_points.txt
zenetics-0.3.3.dist-info/RECORD
