Metadata-Version: 2.3
Name: zenetics
Version: 0.3.3
Summary: Zenetics SDK
Author: Zenetics
Author-email: contact@zenetics.io
Requires-Python: >=3.10,<3.14
Classifier: Programming Language :: Python :: 3
Classifier: Programming Language :: Python :: 3.10
Classifier: Programming Language :: Python :: 3.11
Classifier: Programming Language :: Python :: 3.12
Classifier: Programming Language :: Python :: 3.13
Requires-Dist: httpx (>=0.28.0)
Requires-Dist: pydantic (>=2.10.6,<3.0.0)
Requires-Dist: pydantic-settings (>=2.7.1,<3.0.0)
Requires-Dist: python-dotenv (>=1.1.0,<2.0.0)
Requires-Dist: requests (==2.32.3)
Requires-Dist: rich (>=13.7.0,<14.0.0)
Requires-Dist: typer (>=0.15.1,<0.16.0)
Project-URL: Homepage, https://github.com/zenetics/zenetics-sdk
Project-URL: Issues, https://github.com/zenetics/zenetics-sdk/issues
